pyfastexcel/__init__.py
pyfastexcel/_typing.py
pyfastexcel/chart.py
pyfastexcel/driver.py
pyfastexcel/enums.py
pyfastexcel/logformatter.py
pyfastexcel/pivot.py
pyfastexcel/pyfastexcel.so
pyfastexcel/serializers.py
pyfastexcel/style.py
pyfastexcel/utils.py
pyfastexcel/validators.py
pyfastexcel/workbook.py
pyfastexcel/worksheet.py
pyfastexcel/writer.py
pyfastexcel-0.1.8.dist-info/LICENSE
pyfastexcel-0.1.8.dist-info/METADATA
pyfastexcel-0.1.8.dist-info/WHEEL
pyfastexcel-0.1.8.dist-info/top_level.txt
pyfastexcel-0.1.8.dist-info/RECORD
