Metadata-Version: 2.1
Name: pyfastexcel
Version: 0.1.8
Summary: High performace excel file generation library.
Home-page: https://github.com/Zncl2222/pyfastexcel
Author: Zncl2222
Author-email: 3002shinning@gmail.com
License: MIT
Classifier: Development Status :: 4 - Beta
Classifier: License :: OSI Approved :: MIT License
Classifier: Programming Language :: Go
Classifier: Programming Language :: Python :: 3
Classifier: Programming Language :: Python :: 3 :: Only
Classifier: Programming Language :: Python :: 3.8
Classifier: Programming Language :: Python :: 3.9
Classifier: Programming Language :: Python :: 3.10
Classifier: Programming Language :: Python :: 3.11
Requires-Python: >=3.8
License-File: LICENSE
Requires-Dist: msgspec
Requires-Dist: openpyxl-style-writer>=1.1.3
Requires-Dist: pydantic
Requires-Dist: eval-type-backport; python_version < "3.9"
